<nodeTypes xmlns:nt="http://www.jcp.org/jcr/nt/1.0" xmlns:mix="http://www.jcp.org/jcr/mix/1.0" xmlns:jcr="http://www.jcp.org/jcr/1.0">

  <nodeType name="exo:statisticItem" isMixin="false" hasOrderableChildNodes="false">
    <supertypes>
      <supertype>mix:referenceable</supertype>
      <supertype>nt:base</supertype>
    </supertypes>
    <propertyDefinitions>
      <propertyDefinition name="executionDate" propertyType="Date" autoCreated="false" mandatory="false" onParentVersion="COPY" protected="false" multiple="false">
        <valueConstraints/>
      </propertyDefinition>
      <propertyDefinition name="year" propertyType="Long" autoCreated="false" mandatory="false" onParentVersion="COPY" protected="false" multiple="false">
        <valueConstraints/>
      </propertyDefinition>
      <propertyDefinition name="type" propertyType="String" autoCreated="false" mandatory="false" onParentVersion="COPY" protected="false" multiple="false">
        <valueConstraints/>
      </propertyDefinition>
      <propertyDefinition name="idInYear" propertyType="Long" autoCreated="false" mandatory="false" onParentVersion="COPY" protected="false" multiple="false">
        <valueConstraints/>
      </propertyDefinition>
    </propertyDefinitions>
    <childNodeDefinitions/>
  </nodeType>
</nodeTypes>